martensite_utils/__init__.py
martensite_utils/from_numpy.py
martensite_utils/message_pb2.py
martensite_utils/send_numpy_array.py
martensite_utils/to_numpy.py
martensite_utils-0.0.2.dist-info/licenses/LICENSE
martensite_utils-0.0.2.dist-info/METADATA
martensite_utils-0.0.2.dist-info/WHEEL
martensite_utils-0.0.2.dist-info/top_level.txt
martensite_utils-0.0.2.dist-info/RECORD
