Metadata-Version: 2.4
Name: martensite-utils
Version: 0.0.2
Summary: A utility library for Stonecrest Data Solution's Martensite ONNX Inference Server
Author-email: Dominik Steinberg <dsteinberg@stonecrestdata.com>
License-Expression: MIT
Classifier: Programming Language :: Python :: 3
Classifier: Operating System :: OS Independent
Classifier: Development Status :: 2 - Pre-Alpha
Requires-Python: >=3.10
License-File: LICENSE
Requires-Dist: certifi==2025.4.26
Requires-Dist: charset-normalizer==3.4.1
Requires-Dist: idna==3.10
Requires-Dist: numpy==2.2.5
Requires-Dist: protobuf==6.30.2
Requires-Dist: requests==2.32.3
Requires-Dist: urllib3==2.4.0
Provides-Extra: test
Requires-Dist: pytest==8.3.5; extra == "test"
Dynamic: license-file
